pyLuogu/__init__.py
pyLuogu/api.py
pyLuogu/async_api.py
pyLuogu/errors.py
pyLuogu/static_api.py
pyLuogu/types.py
pyLuogu/bits/controller.py
pyLuogu/bits/decorators.py
pyLuogu/bits/strings.py
pyLuogu/bits/ultility.py
pyLuogu/bits/🏳️‍⚧️.py
luogu_api_python-0.0.2.dist-info/LICENSE
luogu_api_python-0.0.2.dist-info/METADATA
luogu_api_python-0.0.2.dist-info/WHEEL
luogu_api_python-0.0.2.dist-info/top_level.txt
luogu_api_python-0.0.2.dist-info/RECORD
