Metadata-Version: 2.2
Name: luogu-api-python
Version: 0.0.2
Summary: A Python library to interact with the Luogu online judge system
Author-email: bzy <bzy.cirno@gmail.com>, camber <camber@poi.science>
License:                     GNU GENERAL PUBLIC LICENSE
Requires-Python: >=3.7
License-File: LICENSE
Requires-Dist: requests
Requires-Dist: aiohttp
Requires-Dist: beautifulsoup4
Provides-Extra: dev
Requires-Dist: openai; extra == "dev"
